xl_storage/__init__.py
xl_storage-0.1.7.dist-info/METADATA
xl_storage-0.1.7.dist-info/WHEEL
xl_storage-0.1.7.dist-info/licenses/LICENSE
xl_storage-0.1.7.dist-info/RECORD
